<Room>
  <Saves>
    <SaveRoom>
      <saveindex>09</saveindex>
      <indoor roomarea="02" roomindex="25" doorindex="01" />
      <unused>0000</unused>
      <unused>0000</unused>
      <screenx>0000</screenx>
      <screeny>0000</screeny>
      <samusx>0088</samusx>
      <samusy>0000</samusy>
    </SaveRoom>
  </Saves>
  <index>26</index>
  <area>02</area>
  <x>15</x>
  <y>0A</y>
  <width>01</width>
  <height>01</height>
  <upscroll>70</upscroll>
  <dnscroll>A0</dnscroll>
  <specialGFX>00</specialGFX>
  <Doors>
    <Door>
      <toroom area="02" index="25" />
      <bitflag>00</bitflag>
      <direction>04</direction>
      <doortype>0601</doortype>
      <x>00</x>
      <y>00</y>
      <distance>8000</distance>
      <doorcode>0000</doorcode>
    </Door>
    <Door>
      <toroom area="02" index="36" />
      <bitflag>A0</bitflag>
      <direction>02</direction>
      <doortype>0000</doortype>
      <x>04</x>
      <y>00</y>
      <distance>0000</distance>
      <doorcode>0000</doorcode>
    </Door>
    <Elevator />
    <Door>
      <toroom area="02" index="34" />
      <bitflag>00</bitflag>
      <direction>05</direction>
      <doortype>060E</doortype>
      <x>00</x>
      <y>00</y>
      <distance>8000</distance>
      <doorcode>0000</doorcode>
    </Door>
  </Doors>
  <States>
    <State condition="default">
      <LevelData>00 02 0D 85 0D 85 0D 85 0D 85 0D 85 0D 85 0D 85 0D 85 0D 85 0D 85 0D 85 0D 85 0D 85 0D 85 0D 85 0D 85 0D 85 0D 85 0D 85 0D 85 0D 85 0D 85 0D 85 0D 85 0D 85 0D 85 0D 85 0D 85 0D 85 0D 85 0D 85 0D 85 24 81 44 81 47 81 47 81 47 81 44 81 47 81 47 81 47 81 47 81 44 81 47 81 47 81 47 81 44 81 24 85 07 81 46 81 21 85 20 85 1C 85 20 81 21 81 FF 00 FF 00 21 85 20 85 1C 81 20 81 21 81 46 81 07 85 08 8D 08 8D 08 81 02 85 06 89 05 81 07 81 FF 00 FF 00 07 85 05 85 06 8D 02 81 08 85 08 89 08 89 0C 85 08 11 25 15 FF 00 09 01 09 01 09 01 FF 00 FF 00 09 05 09 05 09 05 FF 00 25 11 08 15 0C 81 40 94 0C C4 FF 00 FF 00 FF 00 FF 00 FF 00 FF 00 FF 00 FF 00 FF 00 FF 00 FF 00 FF 00 0C C0 40 90 60 94 2C D4 FF 00 FF 00 FF 00 FF 00 FF 00 FF 00 FF 00 FF 00 FF 00 FF 00 FF 00 FF 00 2C D0 60 90 60 9C 2C DC FF 00 FF 00 FF 00 FF 00 FF 00 FF 00 FF 00 FF 00 FF 00 FF 00 FF 00 FF 00 2C D8 60 98 40 9C 0C DC FF 00 FF 00 FF 00 FF 00 FF 00 FF 00 FF 00 FF 00 FF 00 FF 00 FF 00 FF 00 0C D8 40 98 08 89 1C 85 1D 85 06 81 41 81 4A 81 41 81 FF 90 FF 90 41 81 4A 81 41 81 06 85 1D 81 1C 81 08 8D 1A 85 08 89 0E 81 08 89 46 81 4B 81 46 81 FF 00 FF 00 46 81 4B 81 46 81 08 8D 0E 81 08 8D 1A 81 16 85 13 85 1A 85 08 89 41 81 47 81 41 81 FF 00 FF 00 41 81 47 81 41 81 08 8D 1A 81 13 81 16 81 0D 81 0D 81 14 85 08 89 0E 81 06 81 46 81 FF 00 FF 00 46 81 06 85 0E 81 08 8D 14 81 0D 85 0D 85 0D 81 0D 81 16 85 13 85 1A 85 08 89 44 81 FF 00 FF 00 44 81 08 8D 1A 81 13 81 16 81 0D 85 0D 85 0D 81 0D 81 0D 81 0D 81 16 85 1A 85 08 89 FF 90 FF 90 08 8D 1A 81 16 81 0D 85 0D 85 0D 85 0D 85 00 00 00 00 00 00 00 00 00 00 00 00 00 00 00 00 00 00 00 00 00 00 00 00 00 00 00 00 00 00 00 00 00 00 00 00 00 00 00 00 00 00 00 00 00 00 00 00 00 00 00 00 00 00 00 00 00 00 00 00 00 00 00 00 00 00 00 00 00 00 00 00 00 00 00 00 00 00 00 00 00 93 D2 00 00 00 00 00 00 00 00 00 00 92 93 00 03 41 00 00 00 00 00 00 00 00 00 00 00 00 40 00 03 FF 00 00 00 00 00 00 00 00 00 00 00 00 FF 00 03 FE 00 00 00 00 00 00 00 00 00 00 00 00 FE 00 03 FD 00 00 00 00 00 00 00 00 00 00 00 00 FD 00 00 00 00 00 00 00 00 02 02 00 00 00 00 00 00 00 00 00 00 00 00 00 00 00 00 00 00 00 00 00 00 00 00 00 00 00 00 00 00 00 00 00 00 00 00 00 00 00 00 00 00 00 00 00 00 00 00 00 00 00 00 00 00 00 00 00 00 00 00 00 00 00 00 00 00 00 00 00 00 00 00 00 00 00 00 00 00 01 01 00 00 00 00 00 00 00 </LevelData>
      <GFXset>09</GFXset>
      <music>0515</music>
      <FX1s>
        <FX1 default="true">
          <surfacestart>FFFF</surfacestart>
          <surfacenew>FFFF</surfacenew>
          <surfacespeed>0000</surfacespeed>
          <surfacedelay>00</surfacedelay>
          <type>02</type>
          <transparency1_A>02</transparency1_A>
          <transparency2_B>1E</transparency2_B>
          <liquidflags_C>03</liquidflags_C>
          <paletteflags>1F</paletteflags>
          <animationflags>00</animationflags>
          <paletteblend>02</paletteblend>
        </FX1>
      </FX1s>
      <Enemies killcount="00">
        <Enemy>
          <ID>D73F</ID>
          <X>0080</X>
          <Y>00A0</Y>
          <tilemap>0000</tilemap>
          <special>2C00</special>
          <gfx>0000</gfx>
          <speed>0000</speed>
          <speed2>0140</speed2>
        </Enemy>
      </Enemies>
      <EnemyTypes />
      <layer2scroll>C1C1</layer2scroll>
      <ScrollData>01 </ScrollData>
      <roomvar>0000</roomvar>
      <FX2>0000</FX2>
      <PLMs>
        <PLM>
          <type>B703</type>
          <x>08</x>
          <y>0B</y>
          <ScrollData>
            <Change screen="00" scroll="02" />
          </ScrollData>
        </PLM>
      </PLMs>
      <BGdata>BEC6</BGdata>
      <layer1_2>91F6</layer1_2>
    </State>
  </States>
</Room>