<Room>
  <Saves />
  <index>10</index>
  <area>05</area>
  <x>0C</x>
  <y>13</y>
  <width>06</width>
  <height>02</height>
  <upscroll>70</upscroll>
  <dnscroll>A0</dnscroll>
  <specialGFX>00</specialGFX>
  <Doors>
    <Door>
      <toroom area="05" index="0F" />
      <bitflag>00</bitflag>
      <direction>05</direction>
      <doortype>160E</doortype>
      <x>00</x>
      <y>01</y>
      <distance>8000</distance>
      <doorcode>0000</doorcode>
    </Door>
    <Door>
      <toroom area="05" index="11" />
      <bitflag>00</bitflag>
      <direction>04</direction>
      <doortype>3601</doortype>
      <x>00</x>
      <y>03</y>
      <distance>8000</distance>
      <doorcode>0000</doorcode>
    </Door>
  </Doors>
  <States>
    <State condition="default">
      <LevelData>00 18 44 80 44 80 44 80 44 80 44 80 44 80 44 80 44 80 44 80 44 80 44 80 44 80 44 80 44 80 44 80 44 80 44 80 44 80 44 80 44 80 44 80 44 80 44 80 44 80 44 80 44 80 44 80 44 80 44 80 44 80 44 80 44 80 44 80 44 80 44 80 44 80 44 80 44 80 44 80 44 80 44 80 44 80 44 80 44 80 44 80 44 80 44 80 44 80 44 80 44 80 44 80 44 80 44 80 44 80 44 80 44 80 44 80 44 80 44 80 44 80 44 80 44 80 44 80 44 80 44 80 44 80 44 80 44 80 44 80 44 80 44 80 44 80 44 80 44 80 44 80 44 80 44 80 44 80 44 80 44 80 44 80 44 80 44 80 44 80 44 80 44 80 44 80 44 80 44 80 44 80 44 80 44 80 44 80 44 80 44 80 44 80 44 80 44 80 44 80 44 80 44 80 44 80 44 80 44 80 44 80 44 80 44 80 44 80 44 80 44 80 44 80 44 80 44 80 44 80 44 80 44 80 44 80 44 80 44 80 44 80 44 80 44 80 44 80 44 80 44 80 44 80 44 80 44 80 44 80 44 80 44 80 44 80 44 80 44 80 44 80 44 80 44 80 44 80 44 80 44 80 44 80 44 80 44 80 44 80 44 80 44 80 44 80 44 80 44 80 44 80 44 80 44 80 44 80 44 80 44 80 44 80 44 80 44 80 44 80 44 80 44 80 44 80 44 80 44 80 44 80 44 80 44 80 44 80 44 80 44 80 44 80 44 80 44 80 44 80 44 80 44 80 44 80 44 80 44 80 44 80 44 80 44 80 44 80 44 80 44 80 44 80 44 80 44 80 44 80 44 80 44 80 44 80 E9 82 ED 8A 10 83 16 87 50 83 EF 82 EF 82 50 83 ED 82 E2 82 00 83 01 83 E6 82 10 83 04 83 00 83 01 83 EE 82 03 83 04 83 50 83 EE 82 ED 82 EF 82 EF 82 EF 82 ED 82 EF 82 50 83 35 83 EF 82 E2 82 EF 82 EF 82 ED 82 EF 82 00 83 01 83 02 83 10 83 31 83 07 83 08 83 09 83 10 83 00 83 01 83 30 83 03 83 04 83 05 83 06 83 EE 82 08 83 09 83 EF 82 ED 82 15 83 03 83 04 83 EF 82 EF 82 ED 82 EF 82 ED 82 ED 82 EF 82 EF 82 50 83 50 83 EF 82 ED 82 ED 82 EF 82 EF 82 EF 82 EF 82 EF 82 ED 82 EF 82 ED 82 EF 82 EF 82 EF 82 EF 82 50 83 EF 82 EF 82 EF 82 50 83 ED 82 EF 82 EF 82 50 83 16 83 43 83 E6 82 E9 82 16 8B 10 87 FF 00 FF 00 FF 00 FF 00 07 13 08 13 09 13 00 83 01 83 10 83 10 83 EE 82 00 83 10 83 02 83 E9 82 E6 82 E9 8A 16 83 FF 00 FF 00 FF 00 FF 00 FF 00 FF 00 10 83 FF 00 FF 00 FF 00 FF 00 FF 00 07 13 08 13 09 13 05 83 EE 82 E6 82 31 83 0B 87 EF 82 EE 82 EF 82 50 83 31 83 50 83 EF 82 ED 82 EF 82 0B 83 E6 82 03 83 04 83 00 13 01 13 02 13 FF 00 FF 00 FF 00 FF 00 FF 00 FF 00 FF 00 FF 00 FF 00 FF 00 FF 00 FF 00 FF 00 FF 00 FF 00 FF 00 FF 00 FF 00 FF 00 FF 00 FF 00 FF 00 FF 00 FF 00 FF 00 FF 00 FF 00 FF 00 FF 00 FF 00 FF 00 FF 00 FF 00 FF 00 FF 00 EE 82 E8 82 0B 83 10 83 0B 87 E9 8E FF 00 FF 00 FF 00 FF 00 FF 00 FF 00 03 1B 04 1B 05 8B E9 8A 50 83 15 83 0B 87 EF 82 11 83 EF 82 EF 82 50 83 15 83 FF 00 FF 00 FF 00 FF 00 FF 00 FF 00 EE 82 FF 00 FF 00 FF 00 FF 00 FF 00 FF 00 FF 00 FF 00 FF 00 10 83 08 83 09 83 11 83 12 83 13 83 E2 82 01 83 E6 82 E2 82 15 83 03 83 04 83 00 83 0F 8B 02 13 FF 00 FF 00 FF 00 FF 00 FF 00 FF 00 FF 00 FF 00 FF 00 FF 00 FF 00 FF 00 FF 00 FF 00 FF 00 FF 00 FF 00 FF 00 FF 00 FF 00 FF 00 FF 00 FF 00 FF 00 FF 00 FF 00 FF 00 FF 00 FF 00 FF 00 FF 00 FF 00 FF 00 FF 00 FF 00 FF 00 FF 00 FF 00 FF 00 10 83 E6 82 0E 83 EE 82 FF 00 FF 00 FF 00 FF 00 FF 00 FF 00 FF 00 FF 00 FF 00 FF 00 FF 00 FF 00 FF 00 FF 00 FF 00 FF 00 FF 00 FF 00 FF 00 FF 00 FF 00 FF 00 FF 00 FF 00 FF 00 FF 00 FF 00 EE 82 FF 00 FF 00 FF 00 FF 00 FF 00 FF 00 FF 00 FF 00 FF 00 E9 8A 50 83 50 83 50 83 50 83 15 83 E9 8A ED 82 EF 82 00 13 01 13 02 13 FF 00 FF 00 E8 8E FF 00 FF 00 FF 00 FF 00 FF 00 FF 00 FF 00 FF 00 FF 00 FF 00 FF 00 FF 00 FF 00 FF 00 FF 00 FF 00 FF 00 FF 00 FF 00 FF 00 FF 00 FF 00 FF 00 FF 00 FF 00 FF 00 FF 00 FF 00 FF 00 FF 00 FF 00 FF 00 FF 00 FF 00 FF 00 FF 00 FF 00 FF 00 FF 00 FF 00 E9 8A 00 83 0D 83 EE 82 FF 00 FF 00 FF 00 FF 00 FF 00 FF 00 FF 00 FF 00 FF 00 FF 00 FF 00 FF 00 FF 00 FF 00 FF 00 FF 00 FF 00 FF 00 FF 00 FF 00 FF 00 FF 00 FF 00 FF 00 FF 00 FF 00 FF 00 EE 82 FF 00 FF 00 FF 00 FF 00 FF 00 FF 00 FF 00 FF 00 FF 00 FF 00 FF 00 FF 00 FF 00 FF 00 FF 00 FF 00 FF 00 FF 00 FF 00 FF 00 FF 00 FF 00 FF 00 FF 00 FF 00 FF 00 FF 00 FF 00 FF 00 FF 00 FF 00 FF 00 FF 00 FF 00 FF 00 FF 00 FF 00 FF 00 FF 00 FF 00 FF 00 FF 00 FF 00 FF 00 FF 00 FF 00 FF 00 FF 00 FF 00 FF 00 FF 00 FF 00 FF 00 FF 00 FF 00 FF 00 FF 00 FF 00 FF 00 FF 00 FF 00 FF 00 FF 00 FF 00 0C C0 40 90 0F 83 EE 82 FF 00 FF 00 FF 00 FF 00 FF 00 FF 00 FF 00 FF 00 FF 00 FF 00 FF 00 FF 00 FF 00 FF 00 FF 00 FF 00 FF 00 FF 00 FF 00 FF 00 FF 00 FF 00 FF 00 FF 00 FF 00 FF 00 FF 00 10 83 FF 00 FF 00 FF 00 FF 00 FF 00 FF 00 FF 00 FF 00 FF 00 FF 00 FF 00 FF 00 FF 00 FF 00 FF 00 FF 00 FF 00 FF 00 FF 00 FF 00 FF 00 FF 00 FF 00 FF 00 FF 00 FF 00 FF 00 FF 00 FF 00 16 17 ED 12 EF 12 50 83 EF 82 50 83 EF 82 EF 82 E2 82 50 83 50 83 50 83 E2 82 EF 82 ED 82 EF 82 E2 82 EF 82 EF 82 EF 82 E2 82 EF 82 EF 82 ED 82 EF 82 11 87 13 83 12 83 13 83 11 83 16 83 FF 00 FF 00 FF 00 FF 00 2C D0 60 90 31 83 10 83 FF 00 FF 00 FF 00 FF 00 FF 00 FF 00 FF 00 FF 00 FF 00 FF 00 FF 00 FF 00 FF 00 FF 00 FF 00 FF 00 FF 00 FF 00 FF 00 FF 00 FF 00 FF 00 FF 00 FF 00 FF 00 FF 00 FF 00 EE 82 FF 00 FF 00 FF 00 FF 00 FF 00 FF 00 FF 00 FF 00 FF 00 FF 00 FF 00 FF 00 FF 00 FF 00 FF 00 FF 00 FF 00 FF 00 FF 00 FF 00 FF 00 FF 00 FF 00 FF 00 FF 00 FF 00 FF 00 FF 00 16 17 E9 1E 07 13 08 83 09 83 E8 82 EC 82 E9 82 ED 8A EE 86 EA 82 E6 82 EA 82 EE 82 E2 82 E2 82 E2 82 10 83 E2 82 E2 82 E2 82 10 87 FF 00 FF 00 FF 00 FF 00 FF 00 FF 00 FF 00 FF 00 FF 00 10 83 FF 00 FF 00 FF 00 FF 00 2C D8 60 98 0F 83 EE 82 FF 00 FF 00 FF 00 FF 00 FF 00 51 83 EF 82 EF 82 50 83 EF 82 ED 82 ED 82 ED 82 ED 82 ED 82 EF 82 50 83 EF 82 EF 82 EF 82 EF 82 EF 82 51 87 FF 00 FF 00 FF 00 FF 00 EE 82 FF 00 FF 00 FF 00 FF 00 FF 00 FF 00 FF 00 FF 00 FF 00 FF 00 FF 00 FF 00 FF 00 FF 00 FF 00 FF 00 FF 00 FF 00 FF 00 FF 00 FF 00 FF 00 FF 00 FF 00 FF 00 FF 00 FF 00 16 17 E9 1E 16 17 EF 82 16 83 EC 82 0C 83 EC 82 15 83 EE 82 0E 83 EA 82 EC 82 EA 82 0E 83 E8 82 E8 82 E8 82 10 83 EC 82 EC 82 EC 82 EE 86 FF 00 FF 00 FF 00 FF 00 FF 00 FF 00 FF 00 FF 00 FF 00 EE 82 FF 00 FF 00 FF 00 FF 00 0C D8 40 98 0E 83 EE 82 FF 00 FF 00 FF 00 FF 00 FF 00 FF 00 FF 00 FF 00 FF 00 FF 00 FF 00 FF 00 FF 00 FF 00 FF 00 FF 00 FF 00 FF 00 FF 00 FF 00 FF 00 FF 00 FF 00 FF 00 FF 00 FF 00 FF 00 EE 82 FF 00 FF 00 FF 00 FF 00 FF 00 16 87 ED 82 EF 82 EF 82 EF 82 EF 82 EF 82 ED 82 EF 82 EF 82 EF 82 ED 82 EF 82 EF 82 EF 82 EF 82 50 83 EF 82 EF 82 EF 82 50 83 ED 82 E9 8E EC 82 10 87 ED 82 EF 82 EF 82 51 87 EC 82 ED 82 15 83 15 87 50 83 EC 82 50 83 15 83 15 83 EC 82 EC 82 31 83 EF 82 16 83 30 83 EE 86 FF 00 FF 00 FF 00 FF 00 FF 00 FF 00 FF 00 FF 00 FF 00 0A 83 11 B3 12 B3 13 B3 13 B3 15 8B 00 8B 0C 83 EE 82 FF 00 FF 00 FF 00 FF 00 FF 00 FF 00 FF 00 FF 00 FF 00 FF 00 FF 00 FF 00 FF 00 FF 00 FF 00 FF 00 FF 00 FF 00 FF 00 FF 00 FF 00 FF 00 FF 00 FF 00 FF 00 FF 00 FF 00 10 83 FF 00 FF 00 FF 00 FF 00 FF 00 EE 86 31 83 EA 82 E9 82 E9 86 08 83 09 83 05 83 E9 82 EF 8A ED 8A ED 8A 06 83 03 83 04 83 05 83 EC 82 E3 82 E3 82 10 83 35 87 EF 82 50 83 EC 82 ED 82 ED 82 15 83 EC 82 0E 83 EC 82 00 8B 01 8B 02 8B E9 82 EC 82 EF 8A E9 86 03 83 04 83 ED 82 10 83 06 83 0E 83 EC 82 10 87 FF 00 FF 00 FF 00 FF 00 FF 00 FF 00 FF 00 FF 00 FF 00 EE 82 FF 00 FF 00 FF 00 FF 00 10 83 E6 82 EE 82 10 83 FF 00 FF 00 FF 00 FF 00 FF 00 FF 00 FF 00 FF 00 FF 00 FF 00 FF 00 FF 00 FF 00 FF 00 FF 00 FF 00 FF 00 FF 00 FF 00 FF 00 FF 00 FF 00 FF 00 FF 00 FF 00 FF 00 FF 00 EE 82 FF 00 FF 00 FF 00 FF 00 FF 00 10 87 E6 82 0B 87 35 83 E2 82 00 8B 01 8B 02 8B EE 82 08 83 09 83 00 83 01 83 E6 82 06 83 31 83 31 83 05 83 06 83 10 83 35 87 ED 82 1A 83 1B 83 EF 82 EF 82 ED 82 EF 82 0F 83 EC 82 0B 83 12 83 0B 87 15 83 31 83 03 83 01 83 02 83 EC 82 15 87 35 83 07 83 0F 83 09 83 0A 87 FF 00 FF 00 FF 00 FF 00 FF 00 FF 00 FF 00 FF 00 FF 00 EE 82 FF 00 FF 00 FF 00 FF 00 E9 8A E9 82 E9 8A E2 82 FF 00 FF 00 FF 00 FF 00 FF 00 FF 00 FF 00 FF 00 FF 00 FF 00 FF 00 FF 00 FF 00 FF 00 FF 00 FF 00 FF 00 FF 00 FF 00 FF 00 FF 00 FF 00 FF 00 FF 00 FF 00 FF 00 FF 00 EE 82 FF 00 FF 00 FF 00 FF 00 FF 00 EE 86 31 83 EA 82 E9 8A 10 83 EF 82 ED 82 EF 82 15 83 ED 82 EF 82 ED 82 EF 82 EF 82 50 83 16 83 EC 82 E3 82 E3 82 10 83 10 87 08 8B 09 8B 10 83 ED 82 50 83 EF 82 50 83 E9 8E EC 82 07 83 08 83 09 83 00 83 01 83 E6 82 EE 86 05 83 EC 82 05 83 EE 82 03 83 EE 82 05 83 10 87 FF 00 FF 00 FF 00 FF 00 FF 00 FF 00 FF 00 FF 00 FF 00 EE 82 FF 00 FF 00 FF 00 FF 00 35 87 15 83 EB 82 0A 83 EF 8A 50 8B 51 8F FF 00 FF 00 FF 00 FF 00 FF 00 FF 00 16 87 ED 82 EF 82 EF 82 EF 82 EF 82 ED 82 EF 82 50 83 EF 82 EF 82 EF 82 EF 82 EF 82 EF 82 EF 82 ED 82 EF 82 15 83 FF 00 FF 00 FF 00 FF 00 FF 00 15 87 ED 82 EF 82 EF 82 ED 82 12 83 13 83 ED 82 EF 82 50 83 EF 82 12 83 13 83 ED 82 50 83 15 83 08 83 09 83 EF 82 EF 82 50 83 00 83 01 83 31 83 07 83 08 83 09 83 50 83 EF 82 EF 82 0B 83 EF 82 50 83 00 83 01 83 02 83 15 87 EF 82 EF 82 0B 83 E2 82 EF 82 0B 83 ED 82 E9 8E FF 00 FF 00 FF 00 FF 00 FF 00 FF 00 FF 00 FF 00 FF 00 10 83 FF 00 FF 00 FF 00 FF 00 10 87 E9 82 E3 82 EE 82 FF 00 FF 00 FF 00 FF 00 FF 00 FF 00 FF 00 FF 00 FF 00 10 87 FF 00 FF 00 FF 00 FF 00 FF 00 FF 00 FF 00 FF 00 FF 00 FF 00 FF 00 FF 00 FF 00 FF 00 FF 00 FF 00 FF 00 FF 00 FF 00 FF 00 FF 00 FF 00 FF 00 FF 00 FF 00 FF 00 FF 00 FF 00 FF 00 FF 00 FF 00 FF 00 FF 00 FF 00 FF 00 FF 00 FF 00 FF 00 FF 00 FF 00 FF 00 FF 00 FF 00 FF 00 FF 00 FF 00 FF 00 FF 00 FF 00 FF 00 FF 00 FF 00 FF 00 FF 00 FF 00 FF 00 FF 00 FF 00 FF 00 FF 00 FF 00 FF 00 FF 00 FF 00 FF 00 FF 00 FF 00 FF 00 FF 00 FF 00 FF 00 FF 00 FF 00 FF 00 FF 00 FF 00 FF 00 10 83 FF 00 FF 00 FF 00 FF 00 EE 86 E8 8A E3 82 10 83 FF 00 FF 00 FF 00 FF 00 FF 00 FF 00 FF 00 FF 00 FF 00 EE 86 FF 00 FF 00 FF 00 FF 00 FF 00 FF 00 FF 00 FF 00 FF 00 FF 00 FF 00 FF 00 FF 00 FF 00 FF 00 FF 00 FF 00 FF 00 FF 00 FF 00 FF 00 FF 00 FF 00 FF 00 FF 00 FF 00 FF 00 FF 00 FF 00 FF 00 FF 00 FF 00 FF 00 FF 00 FF 00 FF 00 FF 00 FF 00 FF 00 FF 00 FF 00 FF 00 FF 00 FF 00 FF 00 FF 00 FF 00 FF 00 FF 00 FF 00 FF 00 FF 00 FF 00 FF 00 FF 00 FF 00 FF 00 FF 00 FF 00 FF 00 FF 00 FF 00 FF 00 FF 00 FF 00 FF 00 FF 00 FF 00 FF 00 FF 00 FF 00 FF 00 FF 00 FF 00 FF 00 FF 00 FF 00 EE 82 FF 00 FF 00 FF 00 FF 00 10 87 57 83 50 83 E2 82 FF 00 FF 00 FF 00 FF 00 FF 00 FF 00 FF 00 FF 00 FF 00 10 87 FF 00 FF 00 FF 00 FF 00 FF 00 FF 00 FF 00 FF 00 FF 00 FF 00 FF 00 FF 00 FF 00 FF 00 FF 00 FF 00 FF 00 FF 00 FF 00 FF 00 FF 00 FF 00 FF 00 FF 00 FF 00 FF 00 FF 00 FF 00 FF 00 FF 00 FF 00 FF 00 FF 00 FF 00 FF 00 FF 00 FF 00 FF 00 FF 00 FF 00 FF 00 FF 00 FF 00 FF 00 FF 00 FF 00 FF 00 FF 00 FF 00 FF 00 FF 00 FF 00 FF 00 FF 00 FF 00 FF 00 FF 00 FF 00 FF 00 FF 00 FF 00 FF 00 FF 00 FF 00 FF 00 FF 00 FF 00 FF 00 FF 00 FF 00 FF 00 FF 00 FF 00 FF 00 FF 00 FF 00 FF 00 EE 82 FF 00 FF 00 FF 00 FF 00 EE 86 58 83 EB 82 10 83 FF 00 FF 00 FF 00 FF 00 FF 00 FF 00 FF 00 FF 00 FF 00 EE 86 FF 00 FF 00 FF 00 FF 00 FF 00 FF 00 FF 00 FF 00 FF 00 FF 00 FF 00 FF 00 FF 00 FF 00 FF 00 FF 00 FF 00 FF 00 FF 00 FF 00 FF 00 FF 00 FF 00 FF 00 FF 00 FF 00 FF 00 FF 00 FF 00 FF 00 FF 00 FF 00 FF 00 FF 00 FF 00 FF 00 FF 00 FF 00 FF 00 FF 00 FF 00 FF 00 FF 00 FF 00 FF 00 FF 00 FF 00 FF 00 FF 00 FF 00 FF 00 FF 00 FF 00 FF 00 FF 00 FF 00 FF 00 FF 00 FF 00 FF 00 FF 00 FF 00 FF 00 FF 00 FF 00 FF 00 FF 00 FF 00 FF 00 FF 00 FF 00 FF 00 FF 00 FF 00 FF 00 FF 00 FF 00 EE 82 FF 00 FF 00 FF 00 FF 00 EE 86 E8 82 E3 82 EE 82 FF 00 FF 00 FF 00 FF 00 FF 00 FF 00 FF 00 51 83 ED 82 E6 82 50 83 ED 86 EF 82 EF 82 EF 82 EF 82 50 83 EF 82 EF 82 EF 82 EF 82 ED 82 EF 82 EF 82 EF 82 EF 82 EF 82 EF 82 0B 83 E6 82 0B 87 EF 82 EF 82 EF 82 0B 83 50 83 EF 82 ED 82 EF 82 EF 82 EF 82 EF 82 EF 82 0B 83 50 83 EF 82 ED 82 ED 82 EF 82 EF 82 EF 82 50 83 50 83 EF 82 EF 82 EF 82 0B 83 EF 82 EF 82 50 83 ED 82 EF 82 50 83 0B 83 EF 82 ED 82 EF 82 50 83 EF 82 EF 82 0B 83 EF 82 EF 82 ED 82 EF 82 EF 82 ED 82 EF 82 EF 82 0B 83 50 83 51 87 FF 00 FF 00 FF 00 FF 00 FF 00 10 83 FF 00 FF 00 FF 00 FF 00 EE 86 E9 8A ED 82 15 83 FF 00 FF 00 FF 00 FF 00 FF 00 FF 00 FF 00 FF 00 FF 00 FF 00 FF 00 FF 00 FF 00 FF 00 FF 00 FF 00 FF 00 FF 00 FF 00 FF 00 FF 00 FF 00 FF 00 FF 00 FF 00 FF 00 FF 00 FF 00 FF 00 FF 00 FF 00 FF 00 FF 00 FF 00 FF 00 FF 00 FF 00 FF 00 FF 00 FF 00 FF 00 FF 00 FF 00 FF 00 FF 00 FF 00 FF 00 FF 00 FF 00 FF 00 FF 00 FF 00 FF 00 FF 00 FF 00 FF 00 FF 00 FF 00 FF 00 FF 00 FF 00 FF 00 FF 00 FF 00 FF 00 FF 00 FF 00 FF 00 FF 00 FF 00 FF 00 FF 00 FF 00 FF 00 FF 00 FF 00 FF 00 FF 00 FF 00 FF 00 FF 00 FF 00 FF 00 FF 00 FF 00 FF 00 FF 00 10 83 FF 00 FF 00 FF 00 FF 00 EE 86 E9 82 09 83 EF 82 ED 82 51 87 FF 00 FF 00 FF 00 FF 00 FF 00 FF 00 FF 00 FF 00 FF 00 FF 00 FF 00 FF 00 FF 00 FF 00 FF 00 FF 00 FF 00 FF 00 FF 00 FF 00 FF 00 FF 00 FF 00 FF 00 FF 00 FF 00 FF 00 FF 00 FF 00 FF 00 FF 00 FF 00 FF 00 FF 00 FF 00 FF 00 FF 00 FF 00 FF 00 FF 00 FF 00 FF 00 FF 00 FF 00 FF 00 FF 00 FF 00 FF 00 FF 00 FF 00 FF 00 FF 00 FF 00 FF 00 FF 00 FF 00 FF 00 FF 00 FF 00 FF 00 FF 00 FF 00 FF 00 FF 00 FF 00 FF 00 FF 00 FF 00 FF 00 FF 00 FF 00 FF 00 FF 00 FF 00 FF 00 FF 00 FF 00 FF 00 FF 00 FF 00 FF 00 FF 00 FF 00 FF 00 FF 00 EE 82 FF 00 FF 00 FF 00 FF 00 EE 86 E8 8A 40 94 0C C4 FF 00 FF 00 FF 00 FF 00 FF 00 FF 00 FF 00 FF 00 FF 00 FF 00 FF 00 FF 00 FF 00 FF 00 FF 00 FF 00 FF 00 FF 00 FF 00 FF 00 FF 00 FF 00 FF 00 FF 00 FF 00 FF 00 FF 00 FF 00 FF 00 FF 00 FF 00 FF 00 FF 00 FF 00 FF 00 FF 00 FF 00 FF 00 FF 00 FF 00 FF 00 FF 00 FF 00 FF 00 FF 00 FF 00 FF 00 FF 00 FF 00 FF 00 FF 00 FF 00 FF 00 FF 00 FF 00 FF 00 FF 00 FF 00 FF 00 FF 00 FF 00 FF 00 FF 00 FF 00 FF 00 FF 00 FF 00 FF 00 FF 00 FF 00 FF 00 FF 00 FF 00 FF 00 FF 00 FF 00 FF 00 FF 00 FF 00 FF 00 FF 00 FF 00 FF 00 FF 00 FF 00 FF 00 FF 00 EE 82 FF 00 FF 00 FF 00 FF 00 10 87 57 83 60 94 2C D4 FF 00 FF 00 FF 00 FF 00 FF 00 FF 00 FF 00 FF 00 FF 00 FF 00 FF 00 FF 00 FF 00 FF 00 FF 00 FF 00 FF 00 FF 00 FF 00 FF 00 FF 00 FF 00 FF 00 FF 00 FF 00 FF 00 FF 00 FF 00 FF 00 FF 00 FF 00 FF 00 FF 00 FF 00 FF 00 FF 00 FF 00 FF 00 FF 00 FF 00 FF 00 FF 00 FF 00 FF 00 FF 00 FF 00 FF 00 FF 00 FF 00 FF 00 FF 00 FF 00 FF 00 FF 00 FF 00 FF 00 FF 00 FF 00 FF 00 FF 00 FF 00 FF 00 FF 00 FF 00 FF 00 FF 00 FF 00 FF 00 FF 00 FF 00 FF 00 FF 00 FF 00 FF 00 FF 00 FF 00 FF 00 FF 00 FF 00 FF 00 FF 00 FF 00 FF 00 FF 00 FF 00 FF 00 FF 00 10 83 FF 00 FF 00 FF 00 FF 00 EE 86 58 83 60 9C 2C DC FF 00 FF 00 FF 00 FF 00 FF 00 51 83 ED 82 EF 82 EF 82 EF 82 EF 82 ED 82 EF 82 EF 82 ED 82 50 83 EF 82 EF 82 EF 82 EF 82 EF 82 EF 82 ED 82 EF 82 EF 82 50 83 EF 82 EF 82 50 83 E2 82 50 83 EF 82 EF 82 ED 82 ED 82 EF 82 50 83 EF 82 EF 82 EF 82 EF 82 0B 83 EF 82 EF 82 ED 82 ED 82 EF 82 ED 82 ED 82 ED 82 EF 82 EF 82 50 83 0B 83 0B 83 EF 82 EF 82 EF 82 50 83 EF 82 EF 82 EF 82 50 83 EF 82 ED 82 EF 82 EF 82 EF 82 EF 82 0B 83 50 83 EF 82 EF 82 EF 82 EF 82 EF 82 ED 82 EF 82 EF 82 EF 82 ED 82 EF 82 EF 82 EF 82 EF 82 EF 82 50 83 15 83 FF 00 FF 00 FF 00 FF 00 EE 86 E8 82 40 9C 0C DC FF 00 FF 00 FF 00 FF 00 FF 00 FF 00 FF 00 FF 00 FF 00 FF 00 FF 00 FF 00 FF 00 FF 00 FF 00 FF 00 FF 00 FF 00 FF 00 FF 00 FF 00 FF 00 FF 00 FF 00 FF 00 FF 00 FF 00 FF 00 FF 00 FF 00 FF 00 FF 00 FF 00 FF 00 FF 00 FF 00 FF 00 FF 00 FF 00 FF 00 FF 00 FF 00 FF 00 FF 00 FF 00 FF 00 FF 00 FF 00 FF 00 FF 00 FF 00 FF 00 FF 00 FF 00 FF 00 FF 00 FF 00 FF 00 FF 00 FF 00 FF 00 FF 00 FF 00 FF 00 FF 00 FF 00 FF 00 FF 00 FF 00 FF 00 FF 00 FF 00 FF 00 FF 00 FF 00 FF 00 FF 00 FF 00 FF 00 FF 00 FF 00 FF 00 FF 00 FF 00 FF 00 FF 00 FF 00 FF 00 FF 00 FF 00 FF 00 FF 00 EE 86 E9 8A 09 8B EF 8A ED 8A E9 86 FF 00 FF 00 FF 00 FF 00 FF 00 FF 00 FF 00 FF 00 FF 00 FF 00 FF 00 FF 00 FF 00 FF 00 FF 00 FF 00 FF 00 FF 00 FF 00 FF 00 FF 00 FF 00 FF 00 FF 00 FF 00 FF 00 FF 00 FF 00 FF 00 FF 00 FF 00 FF 00 FF 00 FF 00 FF 00 FF 00 FF 00 FF 00 FF 00 FF 00 FF 00 FF 00 FF 00 FF 00 FF 00 FF 00 FF 00 FF 00 FF 00 FF 00 FF 00 FF 00 FF 00 FF 00 FF 00 FF 00 FF 00 FF 00 FF 00 FF 00 FF 00 FF 00 FF 00 FF 00 FF 00 FF 00 FF 00 FF 00 FF 00 FF 00 FF 00 FF 00 FF 00 FF 00 FF 00 FF 00 FF 00 FF 00 FF 00 FF 00 FF 00 FF 00 FF 00 FF 00 FF 00 FF 00 FF 00 FF 00 FF 00 FF 00 EE 86 E9 82 EF 82 31 83 E6 82 EE 86 FF 00 FF 00 FF 00 FF 00 FF 00 FF 00 FF 00 FF 00 FF 00 FF 00 FF 00 FF 00 FF 00 FF 00 FF 00 FF 00 FF 00 FF 00 FF 00 FF 00 FF 00 FF 00 FF 00 FF 00 FF 00 FF 00 FF 00 FF 00 FF 00 FF 00 FF 00 FF 00 FF 00 FF 00 FF 00 FF 00 FF 00 FF 00 FF 00 FF 00 FF 00 FF 00 FF 00 FF 00 FF 00 FF 00 FF 00 FF 00 FF 00 FF 00 FF 00 FF 00 FF 00 FF 00 FF 00 FF 00 FF 00 FF 00 FF 00 FF 00 FF 00 FF 00 FF 00 FF 00 FF 00 FF 00 FF 00 FF 00 FF 00 FF 00 FF 00 FF 00 FF 00 FF 00 FF 00 FF 00 FF 00 FF 00 FF 00 FF 00 FF 00 FF 00 FF 00 FF 00 FF 00 FF 00 FF 00 FF 00 FF 00 FF 00 EE 86 E8 8A E8 8A 15 87 31 83 EE 86 FF 00 FF 00 FF 00 FF 00 FF 00 FF 00 FF 00 FF 00 FF 00 FF 00 FF 00 FF 00 FF 00 FF 00 FF 00 FF 00 FF 00 FF 00 FF 00 FF 00 FF 00 FF 00 FF 00 FF 00 FF 00 FF 00 FF 00 FF 00 FF 00 FF 00 FF 00 FF 00 FF 00 FF 00 FF 00 FF 00 FF 00 FF 00 FF 00 FF 00 FF 00 FF 00 FF 00 FF 00 FF 00 FF 00 FF 00 FF 00 FF 00 FF 00 FF 00 FF 00 FF 00 FF 00 FF 00 FF 00 FF 00 FF 00 FF 00 FF 00 FF 00 FF 00 FF 00 FF 00 FF 00 FF 00 FF 00 FF 00 FF 00 FF 00 FF 00 FF 00 FF 00 FF 00 FF 00 FF 00 FF 00 FF 00 FF 00 FF 00 FF 00 FF 00 FF 00 FF 00 FF 00 FF 00 FF 00 FF 00 FF 00 FF 00 EE 86 57 83 57 83 E2 82 EC 82 15 87 EF 82 ED 82 EF 82 EF 82 50 83 EF 82 EF 82 EF 82 ED 82 EF 82 EF 82 EF 82 EF 82 50 83 EF 82 EF 82 EF 82 ED 82 EF 82 EF 82 EF 82 50 83 ED 82 EF 82 EF 82 EF 82 ED 82 E2 82 ED 82 ED 82 ED 82 EF 82 EF 82 0B 83 EF 82 EF 82 50 83 EF 82 ED 82 EF 82 EF 82 EF 82 EF 82 EF 82 0B 83 ED 82 EF 82 EF 82 50 83 50 83 EF 82 EF 82 ED 82 EF 82 EF 82 50 83 EF 82 EF 82 50 83 E2 82 ED 82 EF 82 EF 82 ED 82 EF 82 EF 82 0B 83 EF 82 EF 82 EF 82 EF 82 ED 82 E2 82 ED 82 EF 82 EF 82 50 83 EF 82 EF 82 EF 82 EF 82 EF 82 ED 82 EF 82 ED 82 0B 83 0B 83 EF 82 ED 82 ED 82 0A 8F 58 83 E8 82 E2 82 EC 82 E2 82 03 83 04 83 05 83 06 83 EC 82 07 83 08 83 09 83 05 83 06 83 07 83 08 83 09 83 EC 82 06 83 16 87 50 83 ED 82 ED 82 50 83 16 83 EC 82 E2 82 03 83 04 83 05 83 06 83 EE 82 EA 82 EA 82 30 83 03 83 04 83 05 83 06 83 E9 82 EC 82 EF 82 EA 82 EF 82 50 83 11 83 12 83 E6 82 11 83 12 83 13 83 50 83 EC 82 EC 82 ED 82 05 83 06 83 07 83 08 83 EC 82 00 83 01 83 EC 82 EE 82 E9 86 07 83 08 83 09 83 05 83 06 83 07 83 08 83 09 83 00 8B 01 8B E6 82 EE 82 EC 82 12 83 13 83 12 83 13 83 16 83 07 83 EC 82 EC 82 05 83 06 83 E6 82 EC 82 E3 82 EA 82 EA 82 E6 82 EE 86 E8 82 44 80 44 80 44 80 44 80 44 80 44 80 44 80 44 80 44 80 44 80 44 80 44 80 44 80 44 80 44 80 44 80 44 80 44 80 44 80 44 80 44 80 44 80 44 80 44 80 44 80 44 80 44 80 44 80 44 80 44 80 44 80 44 80 44 80 44 80 44 80 44 80 44 80 44 80 44 80 44 80 44 80 44 80 44 80 44 80 44 80 44 80 44 80 44 80 44 80 44 80 44 80 44 80 44 80 44 80 44 80 44 80 44 80 44 80 44 80 44 80 44 80 44 80 44 80 44 80 44 80 44 80 44 80 44 80 44 80 44 80 44 80 44 80 44 80 44 80 44 80 44 80 44 80 44 80 44 80 44 80 44 80 44 80 44 80 44 80 44 80 44 80 44 80 44 80 44 80 44 80 44 80 44 80 44 80 44 80 44 80 44 80 00 00 00 00 00 00 00 00 00 00 00 00 00 00 00 00 00 00 00 00 00 00 00 00 00 00 00 00 00 00 00 00 00 00 00 00 00 00 00 00 00 00 00 00 00 00 00 00 00 00 00 00 00 00 00 00 00 00 00 00 00 00 00 00 00 00 00 00 00 00 00 00 00 00 00 00 00 00 00 00 00 00 00 00 00 00 00 00 00 00 00 00 00 00 00 00 00 00 00 00 00 00 00 00 00 00 00 00 00 00 00 00 00 00 00 00 00 00 00 00 00 00 00 00 00 00 00 00 00 00 00 00 00 00 00 00 00 00 00 00 00 00 00 00 00 00 00 00 00 00 00 00 00 00 00 00 00 00 00 00 00 00 00 00 00 00 00 00 00 00 00 00 00 00 00 00 00 00 00 00 00 00 00 00 00 00 00 00 00 00 00 00 00 00 00 00 00 00 00 00 00 00 00 00 00 00 00 00 00 00 00 00 00 00 00 00 00 00 00 00 00 00 00 00 00 00 00 00 00 00 00 00 00 00 00 00 00 00 00 00 00 00 00 00 00 00 00 00 00 00 00 00 00 00 00 00 00 00 00 00 00 00 00 00 00 00 00 00 00 00 00 00 00 00 00 00 00 00 00 00 00 00 00 00 00 00 00 00 00 00 00 00 00 00 00 00 96 97 93 00 00 00 00 00 00 00 00 00 00 00 00 00 00 00 00 00 00 00 00 00 00 00 00 96 97 93 00 00 00 00 00 00 00 00 00 00 00 00 00 00 00 00 00 00 93 D7 D6 00 00 00 00 00 00 00 00 00 00 00 00 00 00 00 00 00 00 00 00 00 00 00 00 00 00 00 00 00 00 00 00 00 00 00 00 00 00 00 00 00 00 00 00 00 00 00 92 93 00 00 00 00 00 00 00 00 00 00 00 00 00 00 00 00 00 00 00 00 00 00 00 00 00 00 00 00 00 00 00 00 00 00 00 00 00 00 00 00 00 00 D2 00 00 00 00 00 00 00 00 00 00 00 00 00 00 00 00 00 00 00 00 00 00 00 00 00 00 00 00 00 00 00 00 00 00 00 00 00 00 00 00 00 00 00 00 00 00 00 00 00 00 00 00 00 00 00 00 00 00 00 00 00 00 00 00 00 00 00 00 00 00 00 00 00 00 00 00 00 00 00 00 00 00 00 00 00 00 00 00 00 93 D7 D6 00 00 00 00 00 00 00 00 00 00 00 00 00 00 00 00 00 00 00 00 00 00 00 00 00 00 00 00 00 00 00 00 00 00 00 00 00 00 00 00 00 00 00 00 00 00 00 00 00 00 00 00 00 00 00 00 00 00 00 00 00 00 00 00 00 00 00 00 00 00 00 00 00 00 00 00 00 00 00 00 00 00 00 00 00 00 00 00 00 00 00 00 00 00 00 00 00 00 00 00 00 00 00 00 00 00 00 00 00 00 00 00 00 00 00 00 00 00 00 00 00 00 00 00 00 00 00 00 00 00 00 00 00 00 00 00 00 00 00 40 01 00 00 00 00 00 00 00 00 00 00 00 00 00 00 00 00 00 00 00 00 00 00 00 00 00 00 00 00 00 00 00 00 00 00 00 00 00 00 00 00 00 00 00 00 00 00 00 00 00 00 00 00 00 00 00 00 00 00 00 0F 13 13 00 00 00 00 00 00 00 00 00 00 00 00 00 00 00 00 00 00 00 00 00 00 00 00 00 00 00 00 00 00 00 00 FF 01 00 00 00 00 00 00 00 00 00 00 00 00 00 00 00 00 00 00 00 00 00 00 00 00 00 00 00 00 00 00 00 00 00 00 00 00 00 00 00 00 00 00 00 00 00 00 00 00 00 00 00 00 00 00 00 00 00 00 0F 13 13 00 00 00 00 00 00 00 00 00 00 00 00 00 00 00 00 00 00 00 00 00 00 00 00 00 00 00 00 00 00 00 00 00 FE 01 00 00 00 00 00 00 00 00 00 00 00 00 00 00 00 00 00 00 00 00 00 00 00 00 00 00 00 00 00 00 00 00 00 00 00 00 00 00 00 00 00 00 00 00 00 00 00 00 00 00 00 00 00 00 00 00 00 0F 13 13 00 00 00 00 00 00 00 00 00 00 00 00 00 00 00 00 00 00 00 00 00 00 00 00 00 00 00 00 00 00 00 00 00 00 FD 01 00 00 00 00 00 00 00 00 00 00 00 00 00 00 00 00 00 00 00 00 00 00 00 00 00 00 00 00 00 00 00 00 00 00 00 00 00 00 00 00 00 00 00 00 00 00 00 00 00 00 00 00 00 00 00 00 00 00 00 00 00 00 00 00 00 00 00 00 00 00 00 00 00 00 00 00 00 00 00 00 00 00 00 00 00 00 00 00 00 00 0E 0E 0E 0E 00 00 00 00 00 00 00 00 00 00 00 00 00 00 00 00 00 00 00 00 00 00 00 00 00 00 00 00 00 00 00 00 00 00 00 00 00 00 00 00 00 00 00 00 00 00 00 00 00 00 00 00 00 00 00 00 00 00 00 00 00 00 00 00 00 00 00 00 00 00 00 00 00 00 00 00 00 00 00 00 00 00 00 00 00 00 00 00 00 00 00 00 00 00 00 00 00 00 00 00 00 00 00 00 00 00 00 00 00 00 00 00 00 00 00 00 00 00 00 00 00 00 00 00 00 00 00 00 00 00 00 00 00 00 00 00 00 00 00 00 00 00 00 00 00 00 00 00 00 00 00 00 00 00 00 00 00 00 00 00 00 00 00 00 00 00 00 00 00 00 00 00 00 00 00 00 00 00 00 00 00 00 00 00 00 00 00 00 00 00 00 00 00 00 00 00 00 00 00 00 00 00 00 00 00 00 00 00 00 00 00 00 00 00 00 00 00 00 00 00 00 00 00 00 00 00 00 00 00 00 00 00 00 00 00 00 00 00 00 00 00 00 00 00 00 00 00 00 00 00 00 00 00 00 00 00 00 00 00 00 00 00 00 00 00 00 00 00 00 00 00 00 00 00 00 00 00 00 00 00 00 00 00 00 00 00 00 00 00 00 00 00 00 00 00 00 00 00 00 00 00 00 00 00 00 00 00 00 00 00 00 00 00 00 00 00 00 00 00 00 00 00 00 00 00 00 00 00 00 00 00 00 00 00 00 00 00 00 00 00 00 00 00 00 00 00 00 00 00 00 00 00 00 00 00 00 00 00 00 00 00 00 00 00 00 00 00 00 00 00 00 00 00 00 00 00 00 00 00 00 00 00 00 00 00 00 00 00 00 00 00 00 00 00 00 00 00 00 00 00 00 00 00 00 00 00 00 00 00 00 00 00 00 00 00 00 00 00 00 00 00 00 00 00 00 00 00 00 00 00 00 00 00 00 00 00 00 00 00 00 00 00 00 00 00 00 00 00 00 00 00 00 00 00 00 00 00 00 00 00 00 00 00 00 00 00 00 00 00 00 00 00 00 00 00 00 00 00 00 00 00 00 00 00 00 00 00 00 00 00 00 00 00 00 00 00 00 00 00 00 00 00 00 00 00 00 00 00 00 00 00 00 00 00 00 00 00 00 00 00 00 00 00 00 00 00 00 00 00 00 00 00 00 00 00 00 00 00 00 00 00 00 00 00 00 00 00 00 00 00 00 00 00 00 00 00 00 00 00 00 00 00 00 00 00 00 00 00 00 00 00 00 00 00 00 00 00 00 00 00 00 00 00 00 00 00 00 00 00 00 00 00 00 00 00 00 00 00 00 00 00 00 00 00 00 00 00 00 00 00 00 00 00 00 00 00 00 00 00 00 00 00 00 00 00 00 00 00 00 00 00 00 00 00 00 00 00 00 00 00 00 00 00 00 00 00 00 00 00 00 00 00 00 00 00 00 00 00 00 00 00 00 00 00 00 00 00 00 00 00 00 00 00 00 00 00 00 00 00 00 00 00 00 00 00 00 00 00 00 00 00 00 00 00 00 00 00 00 00 00 00 00 00 00 00 00 00 00 00 00 00 00 00 00 00 00 00 00 00 00 00 00 00 00 00 00 00 00 00 00 00 00 00 00 00 00 00 00 00 00 00 00 00 00 00 00 00 00 00 00 00 00 00 00 00 00 00 00 00 00 00 00 00 00 00 00 00 00 00 00 00 00 00 00 00 00 00 00 00 00 00 00 00 00 00 00 00 00 00 00 00 00 00 00 00 00 00 00 00 00 00 00 00 00 00 00 00 00 00 00 00 00 00 00 00 00 00 00 00 00 00 00 00 00 00 00 00 00 00 00 00 00 00 00 00 00 00 00 00 00 00 00 00 00 00 00 00 00 00 00 00 00 00 00 00 00 00 00 00 00 00 00 00 00 00 00 00 00 00 00 00 00 00 00 00 00 00 00 00 00 00 00 00 00 00 00 00 00 00 00 00 00 00 00 00 00 00 00 00 00 00 00 00 00 00 00 00 00 00 00 00 00 00 00 00 00 00 00 00 00 00 00 00 00 00 00 00 00 00 00 00 00 00 00 00 00 00 00 00 00 00 00 00 00 00 00 00 00 00 00 00 00 00 00 00 00 00 00 00 00 00 00 00 00 00 00 00 00 00 00 00 00 00 00 00 00 00 00 00 00 00 00 00 00 00 00 00 00 00 00 00 00 00 00 00 00 00 00 00 00 00 00 00 00 00 00 00 00 00 00 00 00 00 00 00 00 00 00 00 00 00 00 00 00 00 00 00 00 00 00 00 00 00 00 00 00 00 00 00 00 00 00 00 00 00 00 00 00 00 00 00 00 00 00 00 00 00 00 00 41 00 00 00 00 00 00 00 00 00 00 00 00 00 00 00 00 00 00 00 00 00 00 00 00 00 00 00 00 00 00 00 00 00 00 00 00 00 00 00 00 00 00 00 00 00 00 00 00 00 00 00 00 00 00 00 00 00 00 00 00 00 00 00 00 00 00 00 00 00 00 00 00 00 00 00 00 00 00 00 00 00 00 00 00 00 00 00 00 00 00 00 00 00 00 00 FF 00 00 00 00 00 00 00 00 00 00 00 00 00 00 00 00 00 00 00 00 00 00 00 00 00 00 00 00 00 00 00 00 00 00 00 00 00 00 00 00 00 00 00 00 00 00 00 00 00 00 00 00 00 00 00 00 00 00 00 00 00 00 00 00 00 00 00 00 00 00 00 00 00 00 00 00 00 00 00 00 00 00 00 00 00 00 00 00 00 00 00 00 00 00 00 FE 00 00 00 00 00 00 00 00 00 00 00 00 00 00 00 00 00 00 00 00 00 00 00 00 00 00 00 00 00 00 00 00 00 00 00 00 00 00 00 00 00 00 00 00 00 00 00 00 00 00 00 00 00 00 00 00 00 00 00 00 00 00 00 00 00 00 00 00 00 00 00 00 00 00 00 00 00 00 00 00 00 00 00 00 00 00 00 00 00 00 00 00 00 00 00 FD 00 00 00 00 00 00 00 00 00 00 00 00 00 00 00 00 00 00 00 00 00 00 00 00 00 00 00 00 00 00 00 00 00 00 00 00 00 00 00 00 00 00 00 00 00 00 00 00 00 00 00 00 00 00 00 00 00 00 00 00 00 00 00 00 00 00 00 00 00 00 00 00 00 00 00 00 00 00 00 00 00 00 00 00 00 00 00 00 00 00 00 00 00 00 00 00 00 00 00 00 00 00 00 00 00 00 00 00 00 00 00 00 00 00 00 00 00 00 00 00 00 00 00 00 00 00 00 00 00 00 00 00 00 00 00 00 00 00 00 00 00 00 00 00 00 00 00 00 00 00 00 00 00 00 00 00 00 00 00 00 00 00 00 00 00 00 00 00 00 00 00 00 00 00 00 00 00 00 00 00 00 00 00 00 00 00 00 00 00 00 00 00 00 00 00 00 00 00 00 00 00 00 00 00 00 00 00 00 00 00 00 00 00 00 00 00 00 00 00 00 00 00 00 00 00 00 00 00 00 00 00 00 00 00 00 00 00 00 00 00 00 00 00 00 00 00 00 00 00 00 00 00 00 00 00 00 00 00 00 00 00 00 00 00 00 00 00 00 00 00 00 00 00 00 00 00 00 00 00 00 00 00 00 00 00 00 00 00 00 00 00 00 00 00 00 00 00 00 00 00 00 00 00 00 00 00 00 00 00 00 00 00 00 00 00 00 00 00 00 00 00 00 00 00 00 00 00 00 00 00 00 00 00 00 00 00 00 00 00 00 00 00 00 00 00 00 00 00 00 00 00 00 00 00 00 00 00 00 00 00 00 00 00 00 00 00 00 00 00 00 00 00 00 00 00 00 00 00 00 00 00 00 00 00 00 00 00 00 00 00 00 00 00 00 00 00 00 00 00 00 00 00 00 00 00 00 00 00 00 00 00 00 00 00 00 00 00 00 00 00 00 00 00 00 00 00 00 00 00 00 00 00 00 00 00 00 00 00 00 00 00 00 00 00 00 00 00 00 00 00 00 00 00 00 00 00 00 00 00 00 00 00 00 00 00 00 00 00 00 00 00 00 00 00 00 00 00 00 00 00 00 00 00 00 00 00 00 00 00 00 00 00 00 00 00 00 00 00 00 00 00 00 00 00 00 00 00 00 00 00 00 00 00 00 00 00 00 00 00 00 00 00 00 00 00 00 00 00 00 00 00 00 00 00 00 00 00 00 00 00 00 00 00 00 00 00 00 00 00 00 00 00 00 00 00 00 00 00 00 00 00 00 00 00 00 00 00 00 00 00 00 00 00 00 00 00 00 00 00 00 00 00 00 00 00 00 00 00 00 00 00 00 00 00 00 00 00 00 00 00 00 00 00 00 00 00 00 00 00 00 00 00 00 00 00 00 00 00 00 00 00 00 00 00 00 00 00 00 00 00 00 00 00 00 00 00 00 00 00 00 00 00 00 00 00 00 00 00 00 00 00 00 00 00 00 00 00 00 00 00 00 00 00 00 00 00 00 00 00 00 </LevelData>
      <GFXset>0D</GFXset>
      <music>0000</music>
      <FX1s>
        <FX1 default="true">
          <surfacestart>FFFF</surfacestart>
          <surfacenew>FFFF</surfacenew>
          <surfacespeed>0000</surfacespeed>
          <surfacedelay>00</surfacedelay>
          <type>00</type>
          <transparency1_A>02</transparency1_A>
          <transparency2_B>02</transparency2_B>
          <liquidflags_C>00</liquidflags_C>
          <paletteflags>70</paletteflags>
          <animationflags>00</animationflags>
          <paletteblend>00</paletteblend>
        </FX1>
      </FX1s>
      <Enemies killcount="07">
        <Enemy>
          <ID>F793</ID>
          <X>00C0</X>
          <Y>0160</Y>
          <tilemap>0000</tilemap>
          <special>2000</special>
          <gfx>0004</gfx>
          <speed>0000</speed>
          <speed2>0010</speed2>
        </Enemy>
        <Enemy>
          <ID>F793</ID>
          <X>0538</X>
          <Y>0160</Y>
          <tilemap>0000</tilemap>
          <special>2000</special>
          <gfx>0004</gfx>
          <speed>0000</speed>
          <speed2>0010</speed2>
        </Enemy>
        <Enemy>
          <ID>F793</ID>
          <X>0488</X>
          <Y>0160</Y>
          <tilemap>0000</tilemap>
          <special>2000</special>
          <gfx>0004</gfx>
          <speed>0000</speed>
          <speed2>0010</speed2>
        </Enemy>
        <Enemy>
          <ID>F793</ID>
          <X>03D8</X>
          <Y>0160</Y>
          <tilemap>0000</tilemap>
          <special>2000</special>
          <gfx>0004</gfx>
          <speed>0000</speed>
          <speed2>0010</speed2>
        </Enemy>
        <Enemy>
          <ID>F793</ID>
          <X>0478</X>
          <Y>0050</Y>
          <tilemap>0000</tilemap>
          <special>2000</special>
          <gfx>0004</gfx>
          <speed>0000</speed>
          <speed2>0010</speed2>
        </Enemy>
        <Enemy>
          <ID>F793</ID>
          <X>04E0</X>
          <Y>0050</Y>
          <tilemap>0000</tilemap>
          <special>2000</special>
          <gfx>0004</gfx>
          <speed>0000</speed>
          <speed2>0010</speed2>
        </Enemy>
        <Enemy>
          <ID>F793</ID>
          <X>0560</X>
          <Y>0050</Y>
          <tilemap>0000</tilemap>
          <special>2000</special>
          <gfx>0004</gfx>
          <speed>0000</speed>
          <speed2>0010</speed2>
        </Enemy>
      </Enemies>
      <EnemyTypes>
        <Enemy>
          <GFX>F793</GFX>
          <palette>0001</palette>
        </Enemy>
        <Enemy>
          <GFX>D4FF</GFX>
          <palette>0002</palette>
        </Enemy>
      </EnemyTypes>
      <layer2scroll>C1C1</layer2scroll>
      <ScrollData>02 02 02 02 02 02 01 01 01 01 01 01 </ScrollData>
      <roomvar>0000</roomvar>
      <FX2>E5A0</FX2>
      <PLMs>
        <PLM>
          <type>DB44</type>
          <x>08</x>
          <y>08</y>
          <arg>0004</arg>
        </PLM>
        <PLM>
          <type>C848</type>
          <x>01</x>
          <y>16</y>
          <arg>90AB</arg>
        </PLM>
      </PLMs>
      <BGdata>E46F</BGdata>
      <layer1_2>C946</layer1_2>
    </State>
  </States>
</Room>